LICENSE
MANIFEST.in
README.rst
setup.py
django_telethon_authorization/__init__.py
django_telethon_authorization/admin.py
django_telethon_authorization/apps.py
django_telethon_authorization/exceptions.py
django_telethon_authorization/helpers.py
django_telethon_authorization/models.py
django_telethon_authorization/urls.py
django_telethon_authorization/views.py
django_telethon_authorization.egg-info/PKG-INFO
django_telethon_authorization.egg-info/SOURCES.txt
django_telethon_authorization.egg-info/dependency_links.txt
django_telethon_authorization.egg-info/requires.txt
django_telethon_authorization.egg-info/top_level.txt
django_telethon_authorization/migrations/0001_initial.py
django_telethon_authorization/migrations/0002_auto_20180804_1431.py
django_telethon_authorization/migrations/0003_auto_20180804_1450.py
django_telethon_authorization/migrations/__init__.py