Metadata-Version: 1.1
Name: django-telethon-authorization
Version: 0.2.6
Summary: Provide REST API for Telethon authorization
Home-page: https://github.com/porovozls/django-telethon-authorization
Author: Dmytro Smyk
Author-email: porovozls@gmail.com
License: BSD License
Platform: UNKNOWN
Classifier: Environment :: Web Environment
Classifier: Framework :: Django
Classifier: Intended Audience :: Developers
Classifier: License :: OSI Approved :: BSD License
Classifier: Operating System :: OS Independent
Classifier: Programming Language :: Python
Classifier: Programming Language :: Python :: 3.5
Classifier: Programming Language :: Python :: 3.6
Classifier: Topic :: Internet :: WWW/HTTP
Classifier: Topic :: Internet :: WWW/HTTP :: Dynamic Content
